pyTCTL-0.1.dist-info/METADATA
pyTCTL-0.1.dist-info/RECORD
pyTCTL-0.1.dist-info/WHEEL
pyTCTL-0.1.dist-info/top_level.txt
pytctl/__init__.py
tests/__init__.py
tests/test_dummy.py
