Metadata-Version: 2.1
Name: pyTCTL
Version: 0.1
Summary: A package for Timed CTL model checking in Python
Home-page: https://github.com/stklik/pyTCTL
Author: Stefan Klikovits
Author-email: pytctl@klikovits.net
License: UNKNOWN
Platform: UNKNOWN
Classifier: Programming Language :: Python :: 3
Classifier: License :: OSI Approved :: MIT License
Classifier: Operating System :: OS Independent
